{
  "wallets": [
    {
      "account": "WILD",
      "coin": "LUNC",
      "symbol": "LUNC",
      "amount": 0.841,
      "quantity": 0.841,
      "qty": 0.841,
      "value": 0.00006625398,
      "valueUSDT": 0.00006625398,
      "usdValue": 0.00006625398,
      "price": 0.00007878,
      "note": "active",
      "entryPrice": 0.00008019,
      "pnl": -0.0000011858100000000015,
      "pnlPct": -1.7583239805462059,
      "highSinceEntry": 0.00008203,
      "pctSold": 1,
      "trailingStop": 0.0000787488,
      "hardStop": 0.0000769824,
      "stop": 0.0000787488,
      "targets": [
        {
          "at": "+4%",
          "price": 0.0000833976,
          "sellPct": 25
        },
        {
          "at": "+8%",
          "price": 0.00008660520000000002,
          "sellPct": 33
        },
        {
          "at": "+12%",
          "price": 0.00008981280000000002,
          "sellPct": 50
        },
        {
          "at": "+20%",
          "price": 0.000096228,
          "sellPct": 100
        }
      ]
    },
    {
      "account": "WILD",
      "coin": "ZIG",
      "symbol": "ZIG",
      "amount": 230.17959,
      "quantity": 230.17959,
      "qty": 230.17959,
      "value": 10.2498971427,
      "valueUSDT": 10.2498971427,
      "usdValue": 10.2498971427,
      "price": 0.04453,
      "note": "active",
      "entryPrice": 0.04339,
      "pnl": 0.26240473260000047,
      "pnlPct": 2.627333486978567,
      "highSinceEntry": 0.04463,
      "pctSold": 0,
      "trailingStop": 0.0428448,
      "hardStop": 0.041654399999999994,
      "stop": 0.0428448,
      "targets": [
        {
          "at": "+4%",
          "price": 0.0451256,
          "sellPct": 25
        },
        {
          "at": "+8%",
          "price": 0.0468612,
          "sellPct": 33
        },
        {
          "at": "+12%",
          "price": 0.0485968,
          "sellPct": 50
        },
        {
          "at": "+20%",
          "price": 0.052067999999999996,
          "sellPct": 100
        }
      ]
    },
    {
      "account": "WILD",
      "coin": "FHE",
      "symbol": "FHE",
      "amount": 359.64,
      "quantity": 359.64,
      "qty": 359.64,
      "value": 9.861328799999999,
      "valueUSDT": 9.861328799999999,
      "usdValue": 9.861328799999999,
      "price": 0.02742,
      "note": "active",
      "entryPrice": 0.0266,
      "pnl": 0.29490480000000047,
      "pnlPct": 3.082706766917309,
      "highSinceEntry": 0.02762,
      "pctSold": 0,
      "trailingStop": 0.0265152,
      "hardStop": 0.025535999999999996,
      "stop": 0.0265152,
      "targets": [
        {
          "at": "+4%",
          "price": 0.027664,
          "sellPct": 25
        },
        {
          "at": "+8%",
          "price": 0.028728,
          "sellPct": 33
        },
        {
          "at": "+12%",
          "price": 0.029792000000000003,
          "sellPct": 50
        },
        {
          "at": "+20%",
          "price": 0.03192,
          "sellPct": 100
        }
      ]
    },
    {
      "account": "WILD",
      "coin": "SWEAT",
      "symbol": "SWEAT",
      "amount": 0.03613,
      "quantity": 0.03613,
      "qty": 0.03613,
      "value": 0.00007058,
      "valueUSDT": 0.00007058,
      "usdValue": 0.00007058,
      "price": 0,
      "note": "active",
      "entryPrice": 0.00224,
      "pnl": null,
      "pnlPct": null,
      "highSinceEntry": 0.00225,
      "pctSold": 1,
      "trailingStop": null,
      "hardStop": null,
      "stop": 0.0021504,
      "targets": null
    },
    {
      "account": "WILD",
      "coin": "USDT",
      "symbol": "USDT",
      "amount": 32.05291258,
      "quantity": 32.05291258,
      "qty": 32.05291258,
      "value": 32.05291258,
      "valueUSDT": 32.05291258,
      "usdValue": 32.05291258,
      "price": 1,
      "note": "disponible",
      "entryPrice": null,
      "pnl": null,
      "pnlPct": null,
      "highSinceEntry": null,
      "pctSold": null,
      "trailingStop": null,
      "hardStop": null,
      "stop": null,
      "targets": null
    },
    {
      "account": "JOAKO",
      "coin": "USDT",
      "symbol": "USDT",
      "amount": 43.05266348,
      "quantity": 43.05266348,
      "qty": 43.05266348,
      "value": 43.05266348,
      "valueUSDT": 43.05266348,
      "usdValue": 43.05266348,
      "price": 1,
      "note": "disponible",
      "entryPrice": null,
      "pnl": null,
      "pnlPct": null,
      "highSinceEntry": null,
      "pctSold": null,
      "trailingStop": null,
      "hardStop": null,
      "stop": null,
      "targets": null
    }
  ],
  "btc": {
    "price": 77943.8,
    "change": -1.6099999999999999
  },
  "watchCoins": [
    {
      "sym": "ZBTUSDT",
      "price": 0.15931,
      "ch24h": 7.13
    },
    {
      "sym": "OPGUSDT",
      "price": 0.2422,
      "ch24h": -6.01
    },
    {
      "sym": "PENGUUSDT",
      "price": 0.008413,
      "ch24h": -3.7900000000000005
    }
  ],
  "totalCapital": 95.21693883667999,
  "capital": 95.21693883667999,
  "wildCapital": 52.164275356679994,
  "joakoCapital": 43.05266348,
  "pnl": -13.113061163320012,
  "pnlPercent": -12.1,
  "startCapital": 108.33,
  "trades": 8,
  "updated": "2026-05-16T14:17:05.528Z"
}