{
  "wallets": [
    {
      "account": "WILD",
      "coin": "ZEREBRO",
      "symbol": "ZEREBRO",
      "amount": 725.274,
      "quantity": 725.274,
      "qty": 725.274,
      "value": 19.81448568,
      "valueUSDT": 19.81448568,
      "usdValue": 19.81448568,
      "price": 0.02732,
      "note": "active",
      "entryPrice": 0.02721,
      "pnl": 0.07978013999999926,
      "pnlPct": 0.4042631385519968,
      "highSinceEntry": 0.02765,
      "pctSold": 0,
      "trailingStop": 0.026544,
      "hardStop": 0.026121600000000002,
      "stop": 0.026544,
      "targets": [
        {
          "at": "+4%",
          "price": 0.0282984,
          "sellPct": 25
        },
        {
          "at": "+8%",
          "price": 0.029386800000000005,
          "sellPct": 33
        },
        {
          "at": "+12%",
          "price": 0.030475200000000004,
          "sellPct": 50
        },
        {
          "at": "+20%",
          "price": 0.032652,
          "sellPct": 100
        }
      ]
    },
    {
      "account": "WILD",
      "coin": "LUNC",
      "symbol": "LUNC",
      "amount": 0.579,
      "quantity": 0.579,
      "qty": 0.579,
      "value": 0.00004343079,
      "valueUSDT": 0.00004343079,
      "usdValue": 0.00004343079,
      "price": 0.00007501,
      "note": "active",
      "entryPrice": 0.000078,
      "pnl": -0.000001731209999999998,
      "pnlPct": -3.833333333333333,
      "highSinceEntry": 0.000078,
      "pctSold": 1,
      "trailingStop": 0.00007488,
      "hardStop": 0.00007488,
      "stop": 0.00007488,
      "targets": [
        {
          "at": "+4%",
          "price": 0.00008112,
          "sellPct": 25
        },
        {
          "at": "+8%",
          "price": 0.00008424,
          "sellPct": 33
        },
        {
          "at": "+12%",
          "price": 0.00008736,
          "sellPct": 50
        },
        {
          "at": "+20%",
          "price": 0.0000936,
          "sellPct": 100
        }
      ]
    },
    {
      "account": "WILD",
      "coin": "PONKE",
      "symbol": "PONKE",
      "amount": 0.0046,
      "quantity": 0.0046,
      "qty": 0.0046,
      "value": 0.00018469,
      "valueUSDT": 0.00018469,
      "usdValue": 0.00018469,
      "price": 0.04015,
      "note": "active",
      "entryPrice": 0.04242,
      "pnl": -0.000010442000000000006,
      "pnlPct": -5.351249410655356,
      "highSinceEntry": 0.04448,
      "pctSold": 0.25,
      "trailingStop": 0.0427008,
      "hardStop": 0.0407232,
      "stop": 0.0427008,
      "targets": [
        {
          "at": "+4%",
          "price": 0.0441168,
          "sellPct": 25
        },
        {
          "at": "+8%",
          "price": 0.0458136,
          "sellPct": 33
        },
        {
          "at": "+12%",
          "price": 0.0475104,
          "sellPct": 50
        },
        {
          "at": "+20%",
          "price": 0.050904,
          "sellPct": 100
        }
      ]
    },
    {
      "account": "WILD",
      "coin": "FF",
      "symbol": "FF",
      "amount": 116.7559,
      "quantity": 116.7559,
      "qty": 116.7559,
      "value": 10.276854318,
      "valueUSDT": 10.276854318,
      "usdValue": 10.276854318,
      "price": 0.08802,
      "note": "active",
      "entryPrice": 0.08543,
      "pnl": 0.3023977809999994,
      "pnlPct": 3.031721877560578,
      "highSinceEntry": 0.08854,
      "pctSold": 0,
      "trailingStop": 0.08499839999999999,
      "hardStop": 0.0820128,
      "stop": 0.08499839999999999,
      "targets": [
        {
          "at": "+4%",
          "price": 0.08884720000000002,
          "sellPct": 25
        },
        {
          "at": "+8%",
          "price": 0.09226440000000001,
          "sellPct": 33
        },
        {
          "at": "+12%",
          "price": 0.09568160000000002,
          "sellPct": 50
        },
        {
          "at": "+20%",
          "price": 0.10251600000000001,
          "sellPct": 100
        }
      ]
    },
    {
      "account": "WILD",
      "coin": "GPS",
      "symbol": "GPS",
      "amount": 0.027,
      "quantity": 0.027,
      "qty": 0.027,
      "value": 0.000198342,
      "valueUSDT": 0.000198342,
      "usdValue": 0.000198342,
      "price": 0.007346,
      "note": "active",
      "entryPrice": 0.008528,
      "pnl": -0.00003191400000000002,
      "pnlPct": -13.860225140712956,
      "highSinceEntry": 0.008575,
      "pctSold": 1,
      "trailingStop": 0.008232,
      "hardStop": 0.00818688,
      "stop": 0.008232,
      "targets": [
        {
          "at": "+4%",
          "price": 0.008869120000000001,
          "sellPct": 25
        },
        {
          "at": "+8%",
          "price": 0.009210240000000001,
          "sellPct": 33
        },
        {
          "at": "+12%",
          "price": 0.009551360000000002,
          "sellPct": 50
        },
        {
          "at": "+20%",
          "price": 0.0102336,
          "sellPct": 100
        }
      ]
    },
    {
      "account": "WILD",
      "coin": "CGPT",
      "symbol": "CGPT",
      "amount": 0.0063,
      "quantity": 0.0063,
      "qty": 0.0063,
      "value": 0.000216405,
      "valueUSDT": 0.000216405,
      "usdValue": 0.000216405,
      "price": 0.03435,
      "note": "active",
      "entryPrice": 0.04089,
      "pnl": -0.00004120200000000002,
      "pnlPct": -15.994130594277333,
      "highSinceEntry": 0.04157,
      "pctSold": 1,
      "trailingStop": 0.039907200000000004,
      "hardStop": 0.0392544,
      "stop": 0.039907200000000004,
      "targets": [
        {
          "at": "+4%",
          "price": 0.042525600000000004,
          "sellPct": 25
        },
        {
          "at": "+8%",
          "price": 0.044161200000000005,
          "sellPct": 33
        },
        {
          "at": "+12%",
          "price": 0.045796800000000006,
          "sellPct": 50
        },
        {
          "at": "+20%",
          "price": 0.049068,
          "sellPct": 100
        }
      ]
    },
    {
      "account": "WILD",
      "coin": "TAC",
      "symbol": "TAC",
      "amount": 436.6629,
      "quantity": 436.6629,
      "qty": 436.6629,
      "value": 10.030146813,
      "valueUSDT": 10.030146813,
      "usdValue": 10.030146813,
      "price": 0.02297,
      "note": "active",
      "entryPrice": 0.02288,
      "pnl": 0.03929966099999991,
      "pnlPct": 0.393356643356646,
      "highSinceEntry": 0.02298,
      "pctSold": 0,
      "trailingStop": 0.0220608,
      "hardStop": 0.0219648,
      "stop": 0.0220608,
      "targets": [
        {
          "at": "+4%",
          "price": 0.023795200000000002,
          "sellPct": 25
        },
        {
          "at": "+8%",
          "price": 0.024710400000000004,
          "sellPct": 33
        },
        {
          "at": "+12%",
          "price": 0.025625600000000005,
          "sellPct": 50
        },
        {
          "at": "+20%",
          "price": 0.027456,
          "sellPct": 100
        }
      ]
    },
    {
      "account": "WILD",
      "coin": "RECALL",
      "symbol": "RECALL",
      "amount": 0.0297,
      "quantity": 0.0297,
      "qty": 0.0297,
      "value": 0.001953072,
      "valueUSDT": 0.001953072,
      "usdValue": 0.001953072,
      "price": 0.06576,
      "note": "active",
      "entryPrice": 0.0638,
      "pnl": 0.0000582120000000001,
      "pnlPct": 3.07210031347962,
      "highSinceEntry": 0.06775,
      "pctSold": 0.25,
      "trailingStop": 0.0643625,
      "hardStop": 0.061248,
      "stop": 0.0643625,
      "targets": [
        {
          "at": "+5%",
          "price": 0.06699,
          "sellPct": 25
        },
        {
          "at": "+10%",
          "price": 0.07018,
          "sellPct": 33
        },
        {
          "at": "+15%",
          "price": 0.07336999999999999,
          "sellPct": 50
        },
        {
          "at": "+25%",
          "price": 0.07974999999999999,
          "sellPct": 100
        }
      ]
    },
    {
      "account": "WILD",
      "coin": "ELIZAOS",
      "symbol": "ELIZAOS",
      "amount": 0.0534,
      "quantity": 0.0534,
      "qty": 0.0534,
      "value": 0.00005108244000000001,
      "valueUSDT": 0.00005108244000000001,
      "usdValue": 0.00005108244000000001,
      "price": 0.0009566,
      "note": "active",
      "entryPrice": 0.0010662,
      "pnl": -0.000005852639999999998,
      "pnlPct": -10.279497280060024,
      "highSinceEntry": 0.0010716,
      "pctSold": 1,
      "trailingStop": 0.001028736,
      "hardStop": 0.001023552,
      "stop": 0.001028736,
      "targets": [
        {
          "at": "+4%",
          "price": 0.001108848,
          "sellPct": 25
        },
        {
          "at": "+8%",
          "price": 0.0011514960000000001,
          "sellPct": 33
        },
        {
          "at": "+12%",
          "price": 0.001194144,
          "sellPct": 50
        },
        {
          "at": "+20%",
          "price": 0.00127944,
          "sellPct": 100
        }
      ]
    },
    {
      "account": "WILD",
      "coin": "PIEVERSE",
      "symbol": "PIEVERSE",
      "amount": 0.0897,
      "quantity": 0.0897,
      "qty": 0.0897,
      "value": 0.08075691,
      "valueUSDT": 0.08075691,
      "usdValue": 0.08075691,
      "price": 0.9003,
      "note": "active",
      "entryPrice": 0.9665,
      "pnl": -0.005938140000000003,
      "pnlPct": -6.849456802897058,
      "highSinceEntry": 0.9786,
      "pctSold": 1,
      "trailingStop": 0.939456,
      "hardStop": 0.92784,
      "stop": 0.939456,
      "targets": [
        {
          "at": "+4%",
          "price": 1.00516,
          "sellPct": 25
        },
        {
          "at": "+8%",
          "price": 1.0438200000000002,
          "sellPct": 33
        },
        {
          "at": "+12%",
          "price": 1.08248,
          "sellPct": 50
        },
        {
          "at": "+20%",
          "price": 1.1598,
          "sellPct": 100
        }
      ]
    },
    {
      "account": "WILD",
      "coin": "SWEAT",
      "symbol": "SWEAT",
      "amount": 0.03613,
      "quantity": 0.03613,
      "qty": 0.03613,
      "value": 0.00007057,
      "valueUSDT": 0.00007057,
      "usdValue": 0.00007057,
      "price": 0,
      "note": "active",
      "entryPrice": 0.00224,
      "pnl": null,
      "pnlPct": null,
      "highSinceEntry": 0.00225,
      "pctSold": 1,
      "trailingStop": null,
      "hardStop": null,
      "stop": 0.0021504,
      "targets": null
    },
    {
      "account": "WILD",
      "coin": "USDT",
      "symbol": "USDT",
      "amount": 12.18078063,
      "quantity": 12.18078063,
      "qty": 12.18078063,
      "value": 12.18078063,
      "valueUSDT": 12.18078063,
      "usdValue": 12.18078063,
      "price": 1,
      "note": "disponible",
      "entryPrice": null,
      "pnl": null,
      "pnlPct": null,
      "highSinceEntry": null,
      "pctSold": null,
      "trailingStop": null,
      "hardStop": null,
      "stop": null,
      "targets": null
    },
    {
      "account": "JOAKO",
      "coin": "USDT",
      "symbol": "USDT",
      "amount": 43.08939275,
      "quantity": 43.08939275,
      "qty": 43.08939275,
      "value": 43.08939275,
      "valueUSDT": 43.08939275,
      "usdValue": 43.08939275,
      "price": 1,
      "note": "disponible",
      "entryPrice": null,
      "pnl": null,
      "pnlPct": null,
      "highSinceEntry": null,
      "pctSold": null,
      "trailingStop": null,
      "hardStop": null,
      "stop": null,
      "targets": null
    }
  ],
  "btc": {
    "price": 78357.8,
    "change": -3.08
  },
  "watchCoins": [
    {
      "sym": "ZBTUSDT",
      "price": 0.15628,
      "ch24h": 6.239999999999999
    },
    {
      "sym": "OPGUSDT",
      "price": 0.2388,
      "ch24h": -18.47
    },
    {
      "sym": "PENGUUSDT",
      "price": 0.008509,
      "ch24h": -6.38
    }
  ],
  "totalCapital": 95.47513469323,
  "capital": 95.47513469323,
  "wildCapital": 52.38574194323,
  "joakoCapital": 43.08939275,
  "pnl": -12.854865306769995,
  "pnlPercent": -11.87,
  "startCapital": 108.33,
  "trades": 8,
  "updated": "2026-05-16T07:56:36.753Z"
}