{
  "wallets": [
    {
      "account": "WILD",
      "coin": "SWEAT",
      "symbol": "SWEAT",
      "amount": 0.03613,
      "quantity": 0.03613,
      "qty": 0.03613,
      "value": 0.00007056,
      "valueUSDT": 0.00007056,
      "usdValue": 0.00007056,
      "price": 0,
      "note": "active",
      "entryPrice": 0.00224,
      "pnl": null,
      "pnlPct": null,
      "highSinceEntry": 0.00225,
      "pctSold": 1,
      "trailingStop": null,
      "hardStop": null,
      "stop": 0.0021504,
      "targets": null
    },
    {
      "account": "WILD",
      "coin": "USDT",
      "symbol": "USDT",
      "amount": 45.57534676,
      "quantity": 45.57534676,
      "qty": 45.57534676,
      "value": 45.57534676,
      "valueUSDT": 45.57534676,
      "usdValue": 45.57534676,
      "price": 1,
      "note": "disponible",
      "entryPrice": null,
      "pnl": null,
      "pnlPct": null,
      "highSinceEntry": null,
      "pctSold": null,
      "trailingStop": null,
      "hardStop": null,
      "stop": null,
      "targets": null
    },
    {
      "account": "JOAKO",
      "coin": "FLOCK",
      "symbol": "FLOCK",
      "amount": 0.00711,
      "quantity": 0.00711,
      "qty": 0.00711,
      "value": 0.0004773654,
      "valueUSDT": 0.0004773654,
      "usdValue": 0.0004773654,
      "price": 0.06714,
      "note": "active",
      "entryPrice": 0.06379,
      "pnl": 0.00002381850000000004,
      "pnlPct": 5.251606834927114,
      "highSinceEntry": 0.06446,
      "pctSold": 0.5,
      "trailingStop": 0.0618816,
      "hardStop": 0.0612384,
      "stop": 0.0618816,
      "targets": [
        {
          "at": "+1%",
          "price": 0.0644279,
          "sellPct": 50
        },
        {
          "at": "+2.5%",
          "price": 0.06538474999999999,
          "sellPct": 100
        }
      ]
    },
    {
      "account": "JOAKO",
      "coin": "CC",
      "symbol": "CC",
      "amount": 112.0587,
      "quantity": 112.0587,
      "qty": 112.0587,
      "value": 17.202131037,
      "valueUSDT": 17.202131037,
      "usdValue": 17.202131037,
      "price": 0.15351,
      "note": "active",
      "entryPrice": 0.15656,
      "pnl": -0.3417790349999997,
      "pnlPct": -1.9481349003576898,
      "highSinceEntry": 0.15656,
      "pctSold": 0,
      "trailingStop": 0.1502976,
      "hardStop": 0.1502976,
      "stop": 0.1502976,
      "targets": [
        {
          "at": "+1%",
          "price": 0.1581256,
          "sellPct": 50
        },
        {
          "at": "+2.5%",
          "price": 0.16047399999999998,
          "sellPct": 100
        }
      ]
    },
    {
      "account": "JOAKO",
      "coin": "LIT",
      "symbol": "LIT",
      "amount": 0.00718,
      "quantity": 0.00718,
      "qty": 0.00718,
      "value": 0.006286089999999999,
      "valueUSDT": 0.006286089999999999,
      "usdValue": 0.006286089999999999,
      "price": 0.8755,
      "note": "active",
      "entryPrice": 0.877,
      "pnl": -0.000010770000000000408,
      "pnlPct": -0.17103762827822555,
      "highSinceEntry": 0.8858,
      "pctSold": 0.5,
      "trailingStop": 0.850368,
      "hardStop": 0.84192,
      "stop": 0.850368,
      "targets": [
        {
          "at": "+1%",
          "price": 0.8857700000000001,
          "sellPct": 50
        },
        {
          "at": "+2.5%",
          "price": 0.898925,
          "sellPct": 100
        }
      ]
    },
    {
      "account": "JOAKO",
      "coin": "TON",
      "symbol": "TON",
      "amount": 3.02638,
      "quantity": 3.02638,
      "qty": 3.02638,
      "value": 5.86512444,
      "valueUSDT": 5.86512444,
      "usdValue": 5.86512444,
      "price": 1.938,
      "note": "active",
      "entryPrice": 1.949,
      "pnl": -0.03329018000000036,
      "pnlPct": -0.5643919958953414,
      "highSinceEntry": 1.95,
      "pctSold": 0,
      "trailingStop": 1.8719999999999999,
      "hardStop": 1.87104,
      "stop": 1.8719999999999999,
      "targets": [
        {
          "at": "+1%",
          "price": 1.96849,
          "sellPct": 50
        },
        {
          "at": "+2.5%",
          "price": 1.997725,
          "sellPct": 100
        }
      ]
    },
    {
      "account": "JOAKO",
      "coin": "FHE",
      "symbol": "FHE",
      "amount": 0.163,
      "quantity": 0.163,
      "qty": 0.163,
      "value": 0.00461616,
      "valueUSDT": 0.00461616,
      "usdValue": 0.00461616,
      "price": 0.02832,
      "note": "active",
      "entryPrice": 0.02793,
      "pnl": 0.00006357000000000023,
      "pnlPct": 1.3963480128893702,
      "highSinceEntry": 0.02821,
      "pctSold": 0.5,
      "trailingStop": 0.027081599999999997,
      "hardStop": 0.026812799999999998,
      "stop": 0.027081599999999997,
      "targets": [
        {
          "at": "+1%",
          "price": 0.0282093,
          "sellPct": 50
        },
        {
          "at": "+2.5%",
          "price": 0.028628249999999997,
          "sellPct": 100
        }
      ]
    },
    {
      "account": "JOAKO",
      "coin": "KAIA",
      "symbol": "KAIA",
      "amount": 101.504,
      "quantity": 101.504,
      "qty": 101.504,
      "value": 5.371591680000001,
      "valueUSDT": 5.371591680000001,
      "usdValue": 5.371591680000001,
      "price": 0.05292,
      "note": "active",
      "entryPrice": 0.05191,
      "pnl": 0.10251904000000041,
      "pnlPct": 1.9456752070891925,
      "highSinceEntry": 0.05293,
      "pctSold": 0,
      "trailingStop": 0.0508128,
      "hardStop": 0.0498336,
      "stop": 0.0508128,
      "targets": [
        {
          "at": "+1%",
          "price": 0.0524291,
          "sellPct": 50
        },
        {
          "at": "+2.5%",
          "price": 0.05320774999999999,
          "sellPct": 100
        }
      ]
    },
    {
      "account": "JOAKO",
      "coin": "USDT",
      "symbol": "USDT",
      "amount": 14.11674607,
      "quantity": 14.11674607,
      "qty": 14.11674607,
      "value": 14.11674607,
      "valueUSDT": 14.11674607,
      "usdValue": 14.11674607,
      "price": 1,
      "note": "disponible",
      "entryPrice": null,
      "pnl": null,
      "pnlPct": null,
      "highSinceEntry": null,
      "pctSold": null,
      "trailingStop": null,
      "hardStop": null,
      "stop": null,
      "targets": null
    }
  ],
  "btc": {
    "price": 76961,
    "change": -1.53
  },
  "watchCoins": [
    {
      "sym": "ZBTUSDT",
      "price": 0.16495,
      "ch24h": 1.06
    },
    {
      "sym": "OPGUSDT",
      "price": 0.258,
      "ch24h": 1.38
    },
    {
      "sym": "PENGUUSDT",
      "price": 0.008379,
      "ch24h": -0.91
    }
  ],
  "totalCapital": 88.1423901624,
  "capital": 88.1423901624,
  "wildCapital": 45.57541732,
  "joakoCapital": 42.5669728424,
  "pnl": -20.187609837599993,
  "pnlPercent": -18.64,
  "startCapital": 108.33,
  "trades": 8,
  "updated": "2026-05-18T04:41:21.811Z"
}