{
  "wallets": [
    {
      "account": "WILD",
      "coin": "SWEAT",
      "symbol": "SWEAT",
      "amount": 0.03613,
      "quantity": 0.03613,
      "qty": 0.03613,
      "value": 0.00007057,
      "valueUSDT": 0.00007057,
      "usdValue": 0.00007057,
      "price": 0,
      "note": "active",
      "entryPrice": 0.00224,
      "pnl": null,
      "pnlPct": null,
      "highSinceEntry": 0.00225,
      "pctSold": 1,
      "trailingStop": null,
      "hardStop": null,
      "stop": 0.0021504,
      "targets": null
    },
    {
      "account": "WILD",
      "coin": "USDT",
      "symbol": "USDT",
      "amount": 45.81211489,
      "quantity": 45.81211489,
      "qty": 45.81211489,
      "value": 45.81211489,
      "valueUSDT": 45.81211489,
      "usdValue": 45.81211489,
      "price": 1,
      "note": "disponible",
      "entryPrice": null,
      "pnl": null,
      "pnlPct": null,
      "highSinceEntry": null,
      "pctSold": null,
      "trailingStop": null,
      "hardStop": null,
      "stop": null,
      "targets": null
    },
    {
      "account": "JOAKO",
      "coin": "BDXN",
      "symbol": "BDXN",
      "amount": 0.0156,
      "quantity": 0.0156,
      "qty": 0.0156,
      "value": 0.000047236799999999995,
      "valueUSDT": 0.000047236799999999995,
      "usdValue": 0.000047236799999999995,
      "price": 0.003028,
      "note": "active",
      "entryPrice": 0.002775,
      "pnl": 0.000003946799999999996,
      "pnlPct": 9.117117117117113,
      "highSinceEntry": 0.002804,
      "pctSold": 0.5,
      "trailingStop": 0.00269184,
      "hardStop": 0.002664,
      "stop": 0.00269184,
      "targets": [
        {
          "at": "+1%",
          "price": 0.00280275,
          "sellPct": 50
        },
        {
          "at": "+2.5%",
          "price": 0.0028443749999999997,
          "sellPct": 100
        }
      ]
    },
    {
      "account": "JOAKO",
      "coin": "FLOCK",
      "symbol": "FLOCK",
      "amount": 0.00711,
      "quantity": 0.00711,
      "qty": 0.00711,
      "value": 0.00047366819999999997,
      "valueUSDT": 0.00047366819999999997,
      "usdValue": 0.00047366819999999997,
      "price": 0.06662,
      "note": "active",
      "entryPrice": 0.06379,
      "pnl": 0.000020121299999999993,
      "pnlPct": 4.436432042639904,
      "highSinceEntry": 0.06446,
      "pctSold": 0.5,
      "trailingStop": 0.0618816,
      "hardStop": 0.0612384,
      "stop": 0.0618816,
      "targets": [
        {
          "at": "+1%",
          "price": 0.0644279,
          "sellPct": 50
        },
        {
          "at": "+2.5%",
          "price": 0.06538474999999999,
          "sellPct": 100
        }
      ]
    },
    {
      "account": "JOAKO",
      "coin": "CC",
      "symbol": "CC",
      "amount": 0.0587,
      "quantity": 0.0587,
      "qty": 0.0587,
      "value": 0.008921812999999999,
      "valueUSDT": 0.008921812999999999,
      "usdValue": 0.008921812999999999,
      "price": 0.15199,
      "note": "active",
      "entryPrice": 0.15656,
      "pnl": -0.0002682590000000011,
      "pnlPct": -2.9190086867654674,
      "highSinceEntry": 0.15656,
      "pctSold": 1,
      "trailingStop": 0.1502976,
      "hardStop": 0.1502976,
      "stop": 0.1502976,
      "targets": [
        {
          "at": "+1%",
          "price": 0.1581256,
          "sellPct": 50
        },
        {
          "at": "+2.5%",
          "price": 0.16047399999999998,
          "sellPct": 100
        }
      ]
    },
    {
      "account": "JOAKO",
      "coin": "STABLE",
      "symbol": "STABLE",
      "amount": 0.8359,
      "quantity": 0.8359,
      "qty": 0.8359,
      "value": 0.030978454000000002,
      "valueUSDT": 0.030978454000000002,
      "usdValue": 0.030978454000000002,
      "price": 0.03706,
      "note": "active",
      "entryPrice": 0.03739,
      "pnl": -0.00027584699999999747,
      "pnlPct": -0.8825889275207222,
      "highSinceEntry": 0.03752,
      "pctSold": 0,
      "trailingStop": 0.036019199999999994,
      "hardStop": 0.0358944,
      "stop": 0.036019199999999994,
      "targets": [
        {
          "at": "+1%",
          "price": 0.0377639,
          "sellPct": 50
        },
        {
          "at": "+2.5%",
          "price": 0.03832475,
          "sellPct": 100
        }
      ]
    },
    {
      "account": "JOAKO",
      "coin": "LIT",
      "symbol": "LIT",
      "amount": 0.00718,
      "quantity": 0.00718,
      "qty": 0.00718,
      "value": 0.006242291999999999,
      "valueUSDT": 0.006242291999999999,
      "usdValue": 0.006242291999999999,
      "price": 0.8694,
      "note": "active",
      "entryPrice": 0.877,
      "pnl": -0.00005456800000000036,
      "pnlPct": -0.8665906499429887,
      "highSinceEntry": 0.8858,
      "pctSold": 0.5,
      "trailingStop": 0.850368,
      "hardStop": 0.84192,
      "stop": 0.850368,
      "targets": [
        {
          "at": "+1%",
          "price": 0.8857700000000001,
          "sellPct": 50
        },
        {
          "at": "+2.5%",
          "price": 0.898925,
          "sellPct": 100
        }
      ]
    },
    {
      "account": "JOAKO",
      "coin": "TON",
      "symbol": "TON",
      "amount": 0.00638,
      "quantity": 0.00638,
      "qty": 0.00638,
      "value": 0.01249204,
      "valueUSDT": 0.01249204,
      "usdValue": 0.01249204,
      "price": 1.958,
      "note": "active",
      "entryPrice": 1.949,
      "pnl": 0.000057419999999999345,
      "pnlPct": 0.46177526936890256,
      "highSinceEntry": 1.952,
      "pctSold": 0,
      "trailingStop": 1.8739199999999998,
      "hardStop": 1.87104,
      "stop": 1.8739199999999998,
      "targets": [
        {
          "at": "+1%",
          "price": 1.96849,
          "sellPct": 50
        },
        {
          "at": "+2.5%",
          "price": 1.997725,
          "sellPct": 100
        }
      ]
    },
    {
      "account": "JOAKO",
      "coin": "FHE",
      "symbol": "FHE",
      "amount": 0.163,
      "quantity": 0.163,
      "qty": 0.163,
      "value": 0.00471722,
      "valueUSDT": 0.00471722,
      "usdValue": 0.00471722,
      "price": 0.02894,
      "note": "active",
      "entryPrice": 0.02793,
      "pnl": 0.00016463000000000008,
      "pnlPct": 3.6161833154314316,
      "highSinceEntry": 0.02821,
      "pctSold": 0.5,
      "trailingStop": 0.027081599999999997,
      "hardStop": 0.026812799999999998,
      "stop": 0.027081599999999997,
      "targets": [
        {
          "at": "+1%",
          "price": 0.0282093,
          "sellPct": 50
        },
        {
          "at": "+2.5%",
          "price": 0.028628249999999997,
          "sellPct": 100
        }
      ]
    },
    {
      "account": "JOAKO",
      "coin": "OPG",
      "symbol": "OPG",
      "amount": 40.7025,
      "quantity": 40.7025,
      "qty": 40.7025,
      "value": 10.619282250000001,
      "valueUSDT": 10.619282250000001,
      "usdValue": 10.619282250000001,
      "price": 0.2609,
      "note": "active",
      "entryPrice": 0.2621,
      "pnl": -0.04884299999999914,
      "pnlPct": -0.45784051888591026,
      "highSinceEntry": 0.2626,
      "pctSold": 0,
      "trailingStop": 0.252096,
      "hardStop": 0.251616,
      "stop": 0.252096,
      "targets": [
        {
          "at": "+1%",
          "price": 0.264721,
          "sellPct": 50
        },
        {
          "at": "+2.5%",
          "price": 0.26865249999999996,
          "sellPct": 100
        }
      ]
    },
    {
      "account": "JOAKO",
      "coin": "KAIA",
      "symbol": "KAIA",
      "amount": 322.413,
      "quantity": 322.413,
      "qty": 322.413,
      "value": 17.20718181,
      "valueUSDT": 17.20718181,
      "usdValue": 17.20718181,
      "price": 0.05337,
      "note": "active",
      "entryPrice": 0.05357,
      "pnl": -0.06448259999999961,
      "pnlPct": -0.37334328915437087,
      "highSinceEntry": 0.05362,
      "pctSold": 0,
      "trailingStop": 0.0514752,
      "hardStop": 0.0514272,
      "stop": 0.0514752,
      "targets": [
        {
          "at": "+1%",
          "price": 0.0541057,
          "sellPct": 50
        },
        {
          "at": "+2.5%",
          "price": 0.05490924999999999,
          "sellPct": 100
        }
      ]
    },
    {
      "account": "JOAKO",
      "coin": "BILL",
      "symbol": "BILL",
      "amount": 39.4303,
      "quantity": 39.4303,
      "qty": 39.4303,
      "value": 5.461490853,
      "valueUSDT": 5.461490853,
      "usdValue": 5.461490853,
      "price": 0.13851,
      "note": "active",
      "entryPrice": 0.14719,
      "pnl": -0.34225500399999975,
      "pnlPct": -5.897139751341795,
      "highSinceEntry": 0.14719,
      "pctSold": 0,
      "trailingStop": 0.1413024,
      "hardStop": 0.1413024,
      "stop": 0.1413024,
      "targets": [
        {
          "at": "+1%",
          "price": 0.14866189999999999,
          "sellPct": 50
        },
        {
          "at": "+2.5%",
          "price": 0.15086974999999997,
          "sellPct": 100
        }
      ]
    },
    {
      "account": "JOAKO",
      "coin": "USDT",
      "symbol": "USDT",
      "amount": 7.45458425,
      "quantity": 7.45458425,
      "qty": 7.45458425,
      "value": 7.45458425,
      "valueUSDT": 7.45458425,
      "usdValue": 7.45458425,
      "price": 1,
      "note": "disponible",
      "entryPrice": null,
      "pnl": null,
      "pnlPct": null,
      "highSinceEntry": null,
      "pctSold": null,
      "trailingStop": null,
      "hardStop": null,
      "stop": null,
      "targets": null
    }
  ],
  "btc": {
    "price": 76751.1,
    "change": -1.66
  },
  "watchCoins": [
    {
      "sym": "ZBTUSDT",
      "price": 0.16496,
      "ch24h": 4.04
    },
    {
      "sym": "OPGUSDT",
      "price": 0.2613,
      "ch24h": 3
    },
    {
      "sym": "PENGUUSDT",
      "price": 0.008196,
      "ch24h": -2.9000000000000004
    }
  ],
  "totalCapital": 86.61859734699999,
  "capital": 86.61859734699999,
  "wildCapital": 45.812185459999995,
  "joakoCapital": 40.806411886999996,
  "pnl": -21.711402653000007,
  "pnlPercent": -20.04,
  "startCapital": 108.33,
  "trades": 8,
  "updated": "2026-05-18T06:27:32.362Z"
}